Growtopia/__init__.py
Growtopia/exceptions.py
Growtopia/generate.py
Growtopia/packet.py
Growtopia/player.py
Growtopia-0.1.6.dist-info/METADATA
Growtopia-0.1.6.dist-info/WHEEL
Growtopia-0.1.6.dist-info/top_level.txt
Growtopia-0.1.6.dist-info/RECORD
