Metadata-Version: 2.1
Name: Growtopia
Version: 0.1.6
Summary: Growtopia Unofficial API (WIP)
Home-page: UNKNOWN
Author: HanzHaxors
Author-email: hanzhaxors@gmail.com
License: MIT
Platform: UNKNOWN
Requires-Dist: requests
